policyengine_us_data/__init__.py
policyengine_us_data/__version__.py
policyengine_us_data/datasets/__init__.py
policyengine_us_data/datasets/acs/README.md
policyengine_us_data/datasets/acs/__init__.py
policyengine_us_data/datasets/acs/acs.py
policyengine_us_data/datasets/acs/census_acs.py
policyengine_us_data/datasets/cps/__init__.py
policyengine_us_data/datasets/cps/census_cps.py
policyengine_us_data/datasets/cps/cps.py
policyengine_us_data/datasets/cps/enhanced_cps.py
policyengine_us_data/datasets/cps/extended_cps.py
policyengine_us_data/datasets/cps/imputation_parameters.yaml
policyengine_us_data/datasets/cps/small_enhanced_cps.py
policyengine_us_data/datasets/cps/local_area_calibration/__init__.py
policyengine_us_data/datasets/cps/local_area_calibration/block_assignment.py
policyengine_us_data/datasets/cps/local_area_calibration/calibration_utils.py
policyengine_us_data/datasets/cps/local_area_calibration/county_assignment.py
policyengine_us_data/datasets/cps/local_area_calibration/create_stratified_cps.py
policyengine_us_data/datasets/cps/local_area_calibration/fit_calibration_weights.py
policyengine_us_data/datasets/cps/local_area_calibration/matrix_tracer.py
policyengine_us_data/datasets/cps/local_area_calibration/publish_local_area.py
policyengine_us_data/datasets/cps/local_area_calibration/sparse_matrix_builder.py
policyengine_us_data/datasets/cps/local_area_calibration/stacked_dataset_builder.py
policyengine_us_data/datasets/cps/long_term/README.md
policyengine_us_data/datasets/cps/long_term/calibration.py
policyengine_us_data/datasets/cps/long_term/check_calibrated_estimates_interactive.py
policyengine_us_data/datasets/cps/long_term/extract_ssa_costs.py
policyengine_us_data/datasets/cps/long_term/projection_utils.py
policyengine_us_data/datasets/cps/long_term/run_household_projection.py
policyengine_us_data/datasets/cps/long_term/ssa_data.py
policyengine_us_data/datasets/puf/__init__.py
policyengine_us_data/datasets/puf/irs_puf.py
policyengine_us_data-1.61.0.dist-info/METADATA
policyengine_us_data-1.61.0.dist-info/WHEEL
policyengine_us_data-1.61.0.dist-info/top_level.txt
policyengine_us_data-1.61.0.dist-info/RECORD
