Metadata-Version: 2.4
Name: policyengine_us_data
Version: 1.61.0
Summary: A package to create representative microdata for the US.
Author-email: PolicyEngine <hello@policyengine.org>
Classifier: Programming Language :: Python :: 3.12
Classifier: Programming Language :: Python :: 3.13
Requires-Python: <3.14.0,>=3.12
Requires-Dist: policyengine-us>=1.516.0
Requires-Dist: policyengine-core>=3.23.6
Requires-Dist: pandas>=2.3.1
Requires-Dist: requests>=2.25.0
Requires-Dist: tqdm>=4.60.0
Requires-Dist: microdf_python>=1.2.1
Requires-Dist: setuptools>=60
Requires-Dist: microimpute>=1.1.4
Requires-Dist: pip-system-certs>=3.0
Requires-Dist: google-cloud-storage>=2.0.0
Requires-Dist: google-auth>=2.0.0
Requires-Dist: scipy>=1.15.3
Requires-Dist: statsmodels>=0.14.5
Requires-Dist: openpyxl>=3.1.5
Requires-Dist: tables>=3.10.2
Requires-Dist: torch>=2.7.1
Requires-Dist: us>=2.0.0
Requires-Dist: sqlalchemy>=2.0.41
Requires-Dist: sqlmodel>=0.0.24
Requires-Dist: xlrd>=2.0.2
Requires-Dist: spm-calculator>=0.1.0
Requires-Dist: tenacity>=8.0.0
Provides-Extra: calibration
Requires-Dist: samplics; extra == "calibration"
Provides-Extra: l0
Requires-Dist: l0-python; extra == "l0"
